.dockerignore
.editorconfig
.pylintrc
AUTHORS
ChangeLog
Dockerfile
LICENSE
README.rst
mypy.ini
requirements.txt
setup.cfg
setup.py
test-requirements.txt
tox.ini
docs/Makefile
docs/conf.py
docs/index.rst
docs/installation.rst
docs/make.bat
docs/readme.rst
docs/usage.rst
flexfolio/__init__.py
flexfolio/cli.py
flexfolio/flex_statement.py
flexfolio/py.typed
flexfolio/utils.py
flexfolio.egg-info/PKG-INFO
flexfolio.egg-info/SOURCES.txt
flexfolio.egg-info/dependency_links.txt
flexfolio.egg-info/entry_points.txt
flexfolio.egg-info/not-zip-safe
flexfolio.egg-info/pbr.json
flexfolio.egg-info/requires.txt
flexfolio.egg-info/top_level.txt
tests/__init__.py
tests/reports.py
tests/test_flex_statement.py