Metadata-Version: 1.0
Name: flexfolio
Version: 1.0.3
Summary: IB FlexStatement to PyFolio bridge
Home-page: https://github.com/xridge/flexfolio
Author: otto-von-bivouac
Author-email: otto@xridge.io
License: UNKNOWN
Keywords: flexfolio
Platform: UNKNOWN
